mju_univ_auth/__init__.py
mju_univ_auth/__main__.py
mju_univ_auth/config.py
mju_univ_auth/exceptions.py
mju_univ_auth/facade.py
mju_univ_auth/results.py
mju_univ_auth/authenticator/__init__.py
mju_univ_auth/authenticator/base_authenticator.py
mju_univ_auth/authenticator/standard_authenticator.py
mju_univ_auth/domain/__init__.py
mju_univ_auth/domain/student_basicinfo.py
mju_univ_auth/domain/student_card.py
mju_univ_auth/domain/student_changelog.py
mju_univ_auth/fetcher/__init__.py
mju_univ_auth/fetcher/base_fetcher.py
mju_univ_auth/fetcher/student_basicinfo_fetcher.py
mju_univ_auth/fetcher/student_card_fetcher.py
mju_univ_auth/fetcher/student_changelog_fetcher.py
mju_univ_auth/infrastructure/__init__.py
mju_univ_auth/infrastructure/crypto.py
mju_univ_auth/infrastructure/parser.py
mju_univ_auth/utils/__init__.py
mju_univ_auth-0.8.6.dist-info/licenses/LICENSE
tests/conftest.py
tests/integration/__init__.py
tests/integration/test_real_auth.py
tests/integration/test_real_facade.py
tests/mock/__init__.py
tests/mock/test_error_handling.py
tests/mock/test_facade_highlevel.py
tests/mock/test_standard_authenticator.py
tests/mock/test_student_card_fetcher.py
tests/mock/test_student_changelog_fetcher.py
tests/unit/test_domain.py
tests/unit/test_parser.py
mju_univ_auth-0.8.6.dist-info/METADATA
mju_univ_auth-0.8.6.dist-info/WHEEL
mju_univ_auth-0.8.6.dist-info/top_level.txt
mju_univ_auth-0.8.6.dist-info/RECORD
