Metadata-Version: 2.4
Name: mju_univ_auth
Version: 0.8.6
Summary: 명지대학교 학생 인증 및 정보 조회를 위한 Python 라이브러리
Author-email: Shin Nyeon Ki <sygys10293@mju.ac.kr>
License-Expression: MIT
Requires-Python: >=3.10
License-File: LICENSE
Requires-Dist: beautifulsoup4>=4.12.0
Requires-Dist: cryptography>=41.0.0
Requires-Dist: lxml>=4.9.0
Requires-Dist: requests>=2.31.0
Requires-Dist: python-dotenv>=1.0.0
Requires-Dist: pydantic>=2.12.5
Dynamic: license-file
